{
"type": "FeatureCollection",
"name": "Polygon3",
"crs": { "type": "name", "properties": { "name": "urn:ogc:def:crs:OGC:1.3:CRS84" } },
"features": [
{ "type": "Feature", "properties": { "Title": "Enhancing Sustainable Agriculture and Livelihoods Program", "Location": "Brgy. Cancaraja, Pastrana, Leyte", "Leader": "Shirley M. Siozon, MAIEd", "Assistant": null, "Members": "Crizelda Briones,Elena L. Castanas", "DateDura": "March 14, 2022 (3 Years)", "Link": "https://pdfupload.io/docs/fae80cfa" }, "geometry": { "type": "Point", "coordinates": [ 124.89586302761947, 11.122902197260064 ] } },
{ "type": "Feature", "properties": { "Title": "Skills Training of Cancajara Farmers Association (CANFA)", "Location": "Brgy. Cancaraja, Pastrana, Leyte", "Leader": "Shirley M. Siozon, MAIEd", "Assistant": null, "Members": null, "DateDura": null, "Link": "https://pdfupload.io/docs/e547fbe8" }, "geometry": { "type": "Point", "coordinates": [ 124.895893252312774, 11.12246722845976 ] } },
{ "type": "Feature", "properties": { "Title": "Project Kubo", "Location": "Brgy. Cancaraja, Pastrana, Leyte", "Leader": "Jessica V. Pagallaman ", "Assistant": null, "Members": "Leancel Homeres,\nGrace Camasin,\nEliditha Easter H. Gervacio,\nMarilou Avendano,\nMary Jessica Alalid,\nMary Grace Aruta,\nRex Palompon Lyra Escarlan,\nCherie Guy Giray,Harold Harvey Lumpas,Liezel Fabrigaras \nMary Jean Yanger, \nShirley M. Siozon", "DateDura": "March 14, 2022 (1-2 Years)", "Link": "https://pdfupload.io/docs/dda7c905" }, "geometry": { "type": "Point", "coordinates": [ 124.895470106606311, 11.122704484249494 ] } },
{ "type": "Feature", "properties": { "Title": "Sewing for Livelihood and Creativity: Empowering Communities through Skills Development in Sewing", "Location": "Brgy. Cancaraja Pastrana Leyte", "Leader": "Maria Ailyn M. Moreno", "Assistant": null, "Members": "Shirley M. Siozon", "DateDura": "February 20, 2024 (September 2024-September 2025)", "Link": "https://pdfupload.io/docs/538727a3" }, "geometry": { "type": "Point", "coordinates": [ 124.895550705788494, 11.122279400822567 ] } }
]
}
